adjacency/__init__.py
Adjacency-1.0.1.dist-info/METADATA
Adjacency-1.0.1.dist-info/WHEEL
Adjacency-1.0.1.dist-info/top_level.txt
Adjacency-1.0.1.dist-info/RECORD
